[
    {
        "Server": 1044,
        "Area": 1,
        "Slot": 2,
        "ID": 33,
        "Price": 47500000,
        "Size": 2,
        "FirstSeen": 1782813650,
        "LastSeen": 1783135189,
        "State": 0,
        "Participate": 0,
        "Winner": 0,
        "EndTime": 0,
        "UpdateTime": 0,
        "PurchaseType": 2,
        "RegionType": 2
    },
    {
        "Server": 1044,
        "Area": 1,
        "Slot": 20,
        "ID": 46,
        "Price": 20000000,
        "Size": 1,
        "FirstSeen": 1782767024,
        "LastSeen": 1783135191,
        "State": 0,
        "Participate": 0,
        "Winner": 0,
        "EndTime": 0,
        "UpdateTime": 0,
        "PurchaseType": 2,
        "RegionType": 1
    },
    {
        "Server": 1044,
        "Area": 1,
        "Slot": 24,
        "ID": 28,
        "Price": 47500000,
        "Size": 2,
        "FirstSeen": 1782630076,
        "LastSeen": 1783135192,
        "State": 0,
        "Participate": 0,
        "Winner": 0,
        "EndTime": 0,
        "UpdateTime": 0,
        "PurchaseType": 2,
        "RegionType": 2
    },
    {
        "Server": 1044,
        "Area": 1,
        "Slot": 28,
        "ID": 46,
        "Price": 20000000,
        "Size": 1,
        "FirstSeen": 1782954386,
        "LastSeen": 1783135193,
        "State": 0,
        "Participate": 0,
        "Winner": 0,
        "EndTime": 0,
        "UpdateTime": 0,
        "PurchaseType": 2,
        "RegionType": 0
    },
    {
        "Server": 1044,
        "Area": 2,
        "Slot": 3,
        "ID": 25,
        "Price": 16000000,
        "Size": 1,
        "FirstSeen": 1782514900,
        "LastSeen": 1783135193,
        "State": 0,
        "Participate": 0,
        "Winner": 0,
        "EndTime": 0,
        "UpdateTime": 0,
        "PurchaseType": 2,
        "RegionType": 2
    },
    {
        "Server": 1044,
        "Area": 2,
        "Slot": 14,
        "ID": 4,
        "Price": 19000000,
        "Size": 1,
        "FirstSeen": 1783083647,
        "LastSeen": 1783135195,
        "State": 0,
        "Participate": 0,
        "Winner": 0,
        "EndTime": 0,
        "UpdateTime": 0,
        "PurchaseType": 2,
        "RegionType": 2
    },
    {
        "Server": 1044,
        "Area": 2,
        "Slot": 14,
        "ID": 55,
        "Price": 16000000,
        "Size": 1,
        "FirstSeen": 1782540056,
        "LastSeen": 1783135195,
        "State": 0,
        "Participate": 0,
        "Winner": 0,
        "EndTime": 0,
        "UpdateTime": 0,
        "PurchaseType": 2,
        "RegionType": 2
    },
    {
        "Server": 1044,
        "Area": 2,
        "Slot": 26,
        "ID": 35,
        "Price": 42500000,
        "Size": 2,
        "FirstSeen": 1782950552,
        "LastSeen": 1783135196,
        "State": 0,
        "Participate": 0,
        "Winner": 0,
        "EndTime": 0,
        "UpdateTime": 0,
        "PurchaseType": 2,
        "RegionType": 2
    },
    {
        "Server": 1044,
        "Area": 4,
        "Slot": 11,
        "ID": 51,
        "Price": 20000000,
        "Size": 1,
        "FirstSeen": 1782288123,
        "LastSeen": 1783135202,
        "State": 0,
        "Participate": 0,
        "Winner": 0,
        "EndTime": 0,
        "UpdateTime": 0,
        "PurchaseType": 2,
        "RegionType": 2
    }
]