[
    {
        "Server": 1044,
        "Area": 0,
        "Slot": 16,
        "ID": 1,
        "Price": 19000000,
        "Size": 1,
        "FirstSeen": 1774418552,
        "LastSeen": 1774838208,
        "State": 0,
        "Participate": 0,
        "Winner": 0,
        "EndTime": 0,
        "UpdateTime": 0,
        "PurchaseType": 2,
        "RegionType": 0
    },
    {
        "Server": 1044,
        "Area": 1,
        "Slot": 23,
        "ID": 11,
        "Price": 20000000,
        "Size": 1,
        "FirstSeen": 1774022536,
        "LastSeen": 1774838216,
        "State": 0,
        "Participate": 0,
        "Winner": 0,
        "EndTime": 0,
        "UpdateTime": 0,
        "PurchaseType": 2,
        "RegionType": 1
    },
    {
        "Server": 1044,
        "Area": 1,
        "Slot": 24,
        "ID": 60,
        "Price": 19000000,
        "Size": 1,
        "FirstSeen": 1774368089,
        "LastSeen": 1774838216,
        "State": 0,
        "Participate": 0,
        "Winner": 0,
        "EndTime": 0,
        "UpdateTime": 0,
        "PurchaseType": 2,
        "RegionType": 2
    },
    {
        "Server": 1044,
        "Area": 2,
        "Slot": 8,
        "ID": 60,
        "Price": 47500000,
        "Size": 2,
        "FirstSeen": 1774720980,
        "LastSeen": 1774838218,
        "State": 0,
        "Participate": 0,
        "Winner": 0,
        "EndTime": 0,
        "UpdateTime": 0,
        "PurchaseType": 2,
        "RegionType": 2
    },
    {
        "Server": 1044,
        "Area": 2,
        "Slot": 19,
        "ID": 43,
        "Price": 42500000,
        "Size": 2,
        "FirstSeen": 1774620081,
        "LastSeen": 1774838219,
        "State": 0,
        "Participate": 0,
        "Winner": 0,
        "EndTime": 0,
        "UpdateTime": 0,
        "PurchaseType": 2,
        "RegionType": 0
    },
    {
        "Server": 1044,
        "Area": 2,
        "Slot": 24,
        "ID": 12,
        "Price": 16000000,
        "Size": 1,
        "FirstSeen": 1774710898,
        "LastSeen": 1774838220,
        "State": 0,
        "Participate": 0,
        "Winner": 0,
        "EndTime": 0,
        "UpdateTime": 0,
        "PurchaseType": 2,
        "RegionType": 2
    },
    {
        "Server": 1044,
        "Area": 3,
        "Slot": 19,
        "ID": 49,
        "Price": 20000000,
        "Size": 1,
        "FirstSeen": 1774281653,
        "LastSeen": 1774838224,
        "State": 0,
        "Participate": 0,
        "Winner": 0,
        "EndTime": 0,
        "UpdateTime": 0,
        "PurchaseType": 2,
        "RegionType": 0
    },
    {
        "Server": 1044,
        "Area": 3,
        "Slot": 22,
        "ID": 28,
        "Price": 16000000,
        "Size": 1,
        "FirstSeen": 1773832208,
        "LastSeen": 1774838224,
        "State": 0,
        "Participate": 0,
        "Winner": 0,
        "EndTime": 0,
        "UpdateTime": 0,
        "PurchaseType": 2,
        "RegionType": 1
    },
    {
        "Server": 1044,
        "Area": 3,
        "Slot": 25,
        "ID": 8,
        "Price": 20000000,
        "Size": 1,
        "FirstSeen": 1774810894,
        "LastSeen": 1774838224,
        "State": 0,
        "Participate": 0,
        "Winner": 0,
        "EndTime": 0,
        "UpdateTime": 0,
        "PurchaseType": 2,
        "RegionType": 2
    },
    {
        "Server": 1044,
        "Area": 4,
        "Slot": 0,
        "ID": 51,
        "Price": 20000000,
        "Size": 1,
        "FirstSeen": 1774778494,
        "LastSeen": 1774838226,
        "State": 0,
        "Participate": 0,
        "Winner": 0,
        "EndTime": 0,
        "UpdateTime": 0,
        "PurchaseType": 2,
        "RegionType": 2
    }
]