[
    {
        "Server": 1044,
        "Area": 0,
        "Slot": 4,
        "ID": 7,
        "Price": 16000000,
        "Size": 1,
        "FirstSeen": 1748026921,
        "LastSeen": 1748655733,
        "State": 0,
        "Participate": 0,
        "Winner": 0,
        "EndTime": 0,
        "UpdateTime": 0,
        "PurchaseType": 2,
        "RegionType": 2
    },
    {
        "Server": 1044,
        "Area": 0,
        "Slot": 9,
        "ID": 34,
        "Price": 20000000,
        "Size": 1,
        "FirstSeen": 1748379644,
        "LastSeen": 1748655734,
        "State": 0,
        "Participate": 0,
        "Winner": 0,
        "EndTime": 0,
        "UpdateTime": 0,
        "PurchaseType": 2,
        "RegionType": 2
    },
    {
        "Server": 1044,
        "Area": 0,
        "Slot": 12,
        "ID": 34,
        "Price": 20000000,
        "Size": 1,
        "FirstSeen": 1748070052,
        "LastSeen": 1748655734,
        "State": 0,
        "Participate": 0,
        "Winner": 0,
        "EndTime": 0,
        "UpdateTime": 0,
        "PurchaseType": 2,
        "RegionType": 2
    },
    {
        "Server": 1044,
        "Area": 1,
        "Slot": 4,
        "ID": 36,
        "Price": 40000000,
        "Size": 2,
        "FirstSeen": 1748156483,
        "LastSeen": 1748655738,
        "State": 0,
        "Participate": 0,
        "Winner": 0,
        "EndTime": 0,
        "UpdateTime": 0,
        "PurchaseType": 2,
        "RegionType": 2
    },
    {
        "Server": 1044,
        "Area": 1,
        "Slot": 17,
        "ID": 35,
        "Price": 16000000,
        "Size": 1,
        "FirstSeen": 1748300478,
        "LastSeen": 1748655740,
        "State": 1,
        "Participate": 12,
        "Winner": 0,
        "EndTime": 1749049200,
        "UpdateTime": 1748619170,
        "PurchaseType": 2,
        "RegionType": 0
    },
    {
        "Server": 1044,
        "Area": 1,
        "Slot": 25,
        "ID": 21,
        "Price": 17000000,
        "Size": 1,
        "FirstSeen": 1748203279,
        "LastSeen": 1748655742,
        "State": 0,
        "Participate": 0,
        "Winner": 0,
        "EndTime": 0,
        "UpdateTime": 0,
        "PurchaseType": 2,
        "RegionType": 2
    },
    {
        "Server": 1044,
        "Area": 2,
        "Slot": 5,
        "ID": 41,
        "Price": 16000000,
        "Size": 1,
        "FirstSeen": 1748091635,
        "LastSeen": 1748655743,
        "State": 0,
        "Participate": 0,
        "Winner": 0,
        "EndTime": 0,
        "UpdateTime": 0,
        "PurchaseType": 2,
        "RegionType": 2
    },
    {
        "Server": 1044,
        "Area": 2,
        "Slot": 26,
        "ID": 35,
        "Price": 42500000,
        "Size": 2,
        "FirstSeen": 1748019644,
        "LastSeen": 1748655747,
        "State": 0,
        "Participate": 0,
        "Winner": 0,
        "EndTime": 0,
        "UpdateTime": 0,
        "PurchaseType": 2,
        "RegionType": 2
    },
    {
        "Server": 1044,
        "Area": 3,
        "Slot": 6,
        "ID": 19,
        "Price": 20000000,
        "Size": 1,
        "FirstSeen": 1747850562,
        "LastSeen": 1748655749,
        "State": 0,
        "Participate": 0,
        "Winner": 0,
        "EndTime": 0,
        "UpdateTime": 0,
        "PurchaseType": 2,
        "RegionType": 2
    },
    {
        "Server": 1044,
        "Area": 3,
        "Slot": 20,
        "ID": 37,
        "Price": 42500000,
        "Size": 2,
        "FirstSeen": 1748613684,
        "LastSeen": 1748655751,
        "State": 0,
        "Participate": 0,
        "Winner": 0,
        "EndTime": 0,
        "UpdateTime": 0,
        "PurchaseType": 2,
        "RegionType": 1
    },
    {
        "Server": 1044,
        "Area": 3,
        "Slot": 21,
        "ID": 49,
        "Price": 20000000,
        "Size": 1,
        "FirstSeen": 1748346222,
        "LastSeen": 1748655752,
        "State": 0,
        "Participate": 0,
        "Winner": 0,
        "EndTime": 0,
        "UpdateTime": 0,
        "PurchaseType": 2,
        "RegionType": 1
    },
    {
        "Server": 1044,
        "Area": 4,
        "Slot": 6,
        "ID": 18,
        "Price": 17000000,
        "Size": 1,
        "FirstSeen": 1748077292,
        "LastSeen": 1748655754,
        "State": 0,
        "Participate": 0,
        "Winner": 0,
        "EndTime": 0,
        "UpdateTime": 0,
        "PurchaseType": 2,
        "RegionType": 2
    },
    {
        "Server": 1044,
        "Area": 4,
        "Slot": 28,
        "ID": 17,
        "Price": 18000000,
        "Size": 1,
        "FirstSeen": 1748530887,
        "LastSeen": 1748655205,
        "State": 0,
        "Participate": 0,
        "Winner": 0,
        "EndTime": 0,
        "UpdateTime": 0,
        "PurchaseType": 2,
        "RegionType": 0
    }
]