[
    {
        "Server": 1173,
        "Area": 0,
        "Slot": 4,
        "ID": 31,
        "Price": 19000000,
        "Size": 1,
        "FirstSeen": 1773158444,
        "LastSeen": 1773801089,
        "State": 0,
        "Participate": 0,
        "Winner": 0,
        "EndTime": 0,
        "UpdateTime": 0,
        "PurchaseType": 2,
        "RegionType": 2
    },
    {
        "Server": 1173,
        "Area": 0,
        "Slot": 15,
        "ID": 36,
        "Price": 20000000,
        "Size": 1,
        "FirstSeen": 1773745232,
        "LastSeen": 1773800963,
        "State": 0,
        "Participate": 0,
        "Winner": 0,
        "EndTime": 0,
        "UpdateTime": 0,
        "PurchaseType": 2,
        "RegionType": 2
    },
    {
        "Server": 1173,
        "Area": 0,
        "Slot": 19,
        "ID": 30,
        "Price": 20000000,
        "Size": 1,
        "FirstSeen": 1773157781,
        "LastSeen": 1773800964,
        "State": 1,
        "Participate": 55,
        "Winner": 0,
        "EndTime": 1773932400,
        "UpdateTime": 1773546933,
        "PurchaseType": 2,
        "RegionType": 0
    },
    {
        "Server": 1173,
        "Area": 0,
        "Slot": 20,
        "ID": 1,
        "Price": 19000000,
        "Size": 1,
        "FirstSeen": 1773752432,
        "LastSeen": 1773800964,
        "State": 0,
        "Participate": 0,
        "Winner": 0,
        "EndTime": 0,
        "UpdateTime": 0,
        "PurchaseType": 2,
        "RegionType": 1
    },
    {
        "Server": 1173,
        "Area": 0,
        "Slot": 25,
        "ID": 34,
        "Price": 20000000,
        "Size": 1,
        "FirstSeen": 1772827368,
        "LastSeen": 1773800965,
        "State": 0,
        "Participate": 0,
        "Winner": 0,
        "EndTime": 0,
        "UpdateTime": 0,
        "PurchaseType": 2,
        "RegionType": 2
    },
    {
        "Server": 1173,
        "Area": 1,
        "Slot": 4,
        "ID": 5,
        "Price": 16000000,
        "Size": 1,
        "FirstSeen": 1772809232,
        "LastSeen": 1773800966,
        "State": 0,
        "Participate": 0,
        "Winner": 0,
        "EndTime": 0,
        "UpdateTime": 0,
        "PurchaseType": 2,
        "RegionType": 2
    },
    {
        "Server": 1173,
        "Area": 1,
        "Slot": 17,
        "ID": 21,
        "Price": 17000000,
        "Size": 1,
        "FirstSeen": 1773043231,
        "LastSeen": 1773800968,
        "State": 0,
        "Participate": 0,
        "Winner": 0,
        "EndTime": 0,
        "UpdateTime": 0,
        "PurchaseType": 2,
        "RegionType": 0
    },
    {
        "Server": 1173,
        "Area": 2,
        "Slot": 4,
        "ID": 25,
        "Price": 16000000,
        "Size": 1,
        "FirstSeen": 1773043233,
        "LastSeen": 1773800971,
        "State": 0,
        "Participate": 0,
        "Winner": 0,
        "EndTime": 0,
        "UpdateTime": 0,
        "PurchaseType": 2,
        "RegionType": 2
    },
    {
        "Server": 1173,
        "Area": 2,
        "Slot": 8,
        "ID": 36,
        "Price": 17000000,
        "Size": 1,
        "FirstSeen": 1772964040,
        "LastSeen": 1773800972,
        "State": 0,
        "Participate": 0,
        "Winner": 0,
        "EndTime": 0,
        "UpdateTime": 0,
        "PurchaseType": 2,
        "RegionType": 2
    },
    {
        "Server": 1173,
        "Area": 2,
        "Slot": 9,
        "ID": 41,
        "Price": 16000000,
        "Size": 1,
        "FirstSeen": 1773043234,
        "LastSeen": 1773800972,
        "State": 0,
        "Participate": 0,
        "Winner": 0,
        "EndTime": 0,
        "UpdateTime": 0,
        "PurchaseType": 2,
        "RegionType": 2
    },
    {
        "Server": 1173,
        "Area": 2,
        "Slot": 11,
        "ID": 25,
        "Price": 16000000,
        "Size": 1,
        "FirstSeen": 1773043234,
        "LastSeen": 1773800972,
        "State": 0,
        "Participate": 0,
        "Winner": 0,
        "EndTime": 0,
        "UpdateTime": 0,
        "PurchaseType": 2,
        "RegionType": 2
    },
    {
        "Server": 1173,
        "Area": 2,
        "Slot": 18,
        "ID": 13,
        "Price": 42500000,
        "Size": 2,
        "FirstSeen": 1773043243,
        "LastSeen": 1773800947,
        "State": 0,
        "Participate": 0,
        "Winner": 0,
        "EndTime": 0,
        "UpdateTime": 0,
        "PurchaseType": 2,
        "RegionType": 0
    },
    {
        "Server": 1173,
        "Area": 2,
        "Slot": 18,
        "ID": 60,
        "Price": 47500000,
        "Size": 2,
        "FirstSeen": 1773043243,
        "LastSeen": 1773800947,
        "State": 0,
        "Participate": 0,
        "Winner": 0,
        "EndTime": 0,
        "UpdateTime": 0,
        "PurchaseType": 2,
        "RegionType": 0
    },
    {
        "Server": 1173,
        "Area": 2,
        "Slot": 27,
        "ID": 11,
        "Price": 16000000,
        "Size": 1,
        "FirstSeen": 1773601470,
        "LastSeen": 1773800948,
        "State": 0,
        "Participate": 0,
        "Winner": 0,
        "EndTime": 0,
        "UpdateTime": 0,
        "PurchaseType": 2,
        "RegionType": 0
    },
    {
        "Server": 1173,
        "Area": 3,
        "Slot": 9,
        "ID": 24,
        "Price": 19000000,
        "Size": 1,
        "FirstSeen": 1772917725,
        "LastSeen": 1773800950,
        "State": 1,
        "Participate": 20,
        "Winner": 0,
        "EndTime": 1773932400,
        "UpdateTime": 1773581689,
        "PurchaseType": 2,
        "RegionType": 2
    },
    {
        "Server": 1173,
        "Area": 4,
        "Slot": 14,
        "ID": 38,
        "Price": 19000000,
        "Size": 1,
        "FirstSeen": 1773072080,
        "LastSeen": 1773800956,
        "State": 0,
        "Participate": 0,
        "Winner": 0,
        "EndTime": 0,
        "UpdateTime": 0,
        "PurchaseType": 2,
        "RegionType": 2
    }
]