[
    {
        "Server": 1174,
        "Area": 0,
        "Slot": 11,
        "ID": 1,
        "Price": 19000000,
        "Size": 1,
        "FirstSeen": 1742065309,
        "LastSeen": 1742694037,
        "State": 0,
        "Participate": 0,
        "Winner": 0,
        "EndTime": 0,
        "UpdateTime": 0,
        "PurchaseType": 2,
        "RegionType": 2
    },
    {
        "Server": 1174,
        "Area": 0,
        "Slot": 26,
        "ID": 4,
        "Price": 20000000,
        "Size": 1,
        "FirstSeen": 1742479258,
        "LastSeen": 1742694039,
        "State": 0,
        "Participate": 0,
        "Winner": 0,
        "EndTime": 0,
        "UpdateTime": 0,
        "PurchaseType": 2,
        "RegionType": 2
    },
    {
        "Server": 1174,
        "Area": 1,
        "Slot": 3,
        "ID": 46,
        "Price": 20000000,
        "Size": 1,
        "FirstSeen": 1741971699,
        "LastSeen": 1742694040,
        "State": 0,
        "Participate": 0,
        "Winner": 0,
        "EndTime": 0,
        "UpdateTime": 0,
        "PurchaseType": 2,
        "RegionType": 2
    },
    {
        "Server": 1174,
        "Area": 1,
        "Slot": 21,
        "ID": 27,
        "Price": 19000000,
        "Size": 1,
        "FirstSeen": 1741636882,
        "LastSeen": 1742694042,
        "State": 0,
        "Participate": 0,
        "Winner": 0,
        "EndTime": 0,
        "UpdateTime": 0,
        "PurchaseType": 2,
        "RegionType": 1
    },
    {
        "Server": 1174,
        "Area": 1,
        "Slot": 21,
        "ID": 58,
        "Price": 47500000,
        "Size": 2,
        "FirstSeen": 1742342645,
        "LastSeen": 1742694042,
        "State": 0,
        "Participate": 0,
        "Winner": 0,
        "EndTime": 0,
        "UpdateTime": 0,
        "PurchaseType": 2,
        "RegionType": 1
    },
    {
        "Server": 1174,
        "Area": 2,
        "Slot": 2,
        "ID": 35,
        "Price": 42500000,
        "Size": 2,
        "FirstSeen": 1741955984,
        "LastSeen": 1742694044,
        "State": 0,
        "Participate": 0,
        "Winner": 0,
        "EndTime": 0,
        "UpdateTime": 0,
        "PurchaseType": 2,
        "RegionType": 2
    },
    {
        "Server": 1174,
        "Area": 2,
        "Slot": 10,
        "ID": 19,
        "Price": 20000000,
        "Size": 1,
        "FirstSeen": 1742482874,
        "LastSeen": 1742694045,
        "State": 0,
        "Participate": 0,
        "Winner": 0,
        "EndTime": 0,
        "UpdateTime": 0,
        "PurchaseType": 2,
        "RegionType": 2
    },
    {
        "Server": 1174,
        "Area": 2,
        "Slot": 19,
        "ID": 5,
        "Price": 42500000,
        "Size": 2,
        "FirstSeen": 1742688050,
        "LastSeen": 1742694046,
        "State": 0,
        "Participate": 0,
        "Winner": 0,
        "EndTime": 0,
        "UpdateTime": 0,
        "PurchaseType": 2,
        "RegionType": 0
    },
    {
        "Server": 1174,
        "Area": 3,
        "Slot": 7,
        "ID": 15,
        "Price": 18000000,
        "Size": 1,
        "FirstSeen": 1742580119,
        "LastSeen": 1742694049,
        "State": 0,
        "Participate": 0,
        "Winner": 0,
        "EndTime": 0,
        "UpdateTime": 0,
        "PurchaseType": 2,
        "RegionType": 2
    },
    {
        "Server": 1174,
        "Area": 3,
        "Slot": 13,
        "ID": 31,
        "Price": 20000000,
        "Size": 1,
        "FirstSeen": 1741698070,
        "LastSeen": 1742694050,
        "State": 0,
        "Participate": 0,
        "Winner": 0,
        "EndTime": 0,
        "UpdateTime": 0,
        "PurchaseType": 2,
        "RegionType": 2
    },
    {
        "Server": 1174,
        "Area": 4,
        "Slot": 4,
        "ID": 47,
        "Price": 18000000,
        "Size": 1,
        "FirstSeen": 1741968138,
        "LastSeen": 1742694053,
        "State": 0,
        "Participate": 0,
        "Winner": 0,
        "EndTime": 0,
        "UpdateTime": 0,
        "PurchaseType": 2,
        "RegionType": 2
    }
]