[
    {
        "Server": 1174,
        "Area": 0,
        "Slot": 15,
        "ID": 2,
        "Price": 47500000,
        "Size": 2,
        "FirstSeen": 1739696432,
        "LastSeen": 1739926188,
        "State": 0,
        "Participate": 0,
        "Winner": 0,
        "EndTime": 0,
        "UpdateTime": 0,
        "PurchaseType": 2,
        "RegionType": 2
    },
    {
        "Server": 1174,
        "Area": 0,
        "Slot": 15,
        "ID": 29,
        "Price": 17000000,
        "Size": 1,
        "FirstSeen": 1739419443,
        "LastSeen": 1739926188,
        "State": 0,
        "Participate": 0,
        "Winner": 0,
        "EndTime": 0,
        "UpdateTime": 0,
        "PurchaseType": 2,
        "RegionType": 2
    },
    {
        "Server": 1174,
        "Area": 1,
        "Slot": 2,
        "ID": 1,
        "Price": 18000000,
        "Size": 1,
        "FirstSeen": 1739288909,
        "LastSeen": 1739926190,
        "State": 0,
        "Participate": 0,
        "Winner": 0,
        "EndTime": 0,
        "UpdateTime": 0,
        "PurchaseType": 2,
        "RegionType": 2
    },
    {
        "Server": 1174,
        "Area": 1,
        "Slot": 11,
        "ID": 33,
        "Price": 47500000,
        "Size": 2,
        "FirstSeen": 1739527238,
        "LastSeen": 1739926191,
        "State": 0,
        "Participate": 0,
        "Winner": 0,
        "EndTime": 0,
        "UpdateTime": 0,
        "PurchaseType": 2,
        "RegionType": 2
    },
    {
        "Server": 1174,
        "Area": 1,
        "Slot": 13,
        "ID": 16,
        "Price": 20000000,
        "Size": 1,
        "FirstSeen": 1739304263,
        "LastSeen": 1739926192,
        "State": 0,
        "Participate": 0,
        "Winner": 0,
        "EndTime": 0,
        "UpdateTime": 0,
        "PurchaseType": 2,
        "RegionType": 2
    },
    {
        "Server": 1174,
        "Area": 1,
        "Slot": 18,
        "ID": 5,
        "Price": 16000000,
        "Size": 1,
        "FirstSeen": 1739433760,
        "LastSeen": 1739926192,
        "State": 0,
        "Participate": 0,
        "Winner": 0,
        "EndTime": 0,
        "UpdateTime": 0,
        "PurchaseType": 2,
        "RegionType": 0
    },
    {
        "Server": 1174,
        "Area": 1,
        "Slot": 25,
        "ID": 57,
        "Price": 19000000,
        "Size": 1,
        "FirstSeen": 1739419450,
        "LastSeen": 1739926193,
        "State": 0,
        "Participate": 0,
        "Winner": 0,
        "EndTime": 0,
        "UpdateTime": 0,
        "PurchaseType": 2,
        "RegionType": 2
    },
    {
        "Server": 1174,
        "Area": 2,
        "Slot": 0,
        "ID": 35,
        "Price": 42500000,
        "Size": 2,
        "FirstSeen": 1739678475,
        "LastSeen": 1739926194,
        "State": 0,
        "Participate": 0,
        "Winner": 0,
        "EndTime": 0,
        "UpdateTime": 0,
        "PurchaseType": 2,
        "RegionType": 2
    },
    {
        "Server": 1174,
        "Area": 2,
        "Slot": 8,
        "ID": 30,
        "Price": 47500000,
        "Size": 2,
        "FirstSeen": 1739340027,
        "LastSeen": 1739926195,
        "State": 0,
        "Participate": 0,
        "Winner": 0,
        "EndTime": 0,
        "UpdateTime": 0,
        "PurchaseType": 2,
        "RegionType": 2
    },
    {
        "Server": 1174,
        "Area": 2,
        "Slot": 10,
        "ID": 11,
        "Price": 16000000,
        "Size": 1,
        "FirstSeen": 1739527250,
        "LastSeen": 1739926196,
        "State": 0,
        "Participate": 0,
        "Winner": 0,
        "EndTime": 0,
        "UpdateTime": 0,
        "PurchaseType": 2,
        "RegionType": 2
    },
    {
        "Server": 1174,
        "Area": 3,
        "Slot": 12,
        "ID": 43,
        "Price": 17000000,
        "Size": 1,
        "FirstSeen": 1739293376,
        "LastSeen": 1739926200,
        "State": 0,
        "Participate": 0,
        "Winner": 0,
        "EndTime": 0,
        "UpdateTime": 0,
        "PurchaseType": 2,
        "RegionType": 2
    },
    {
        "Server": 1174,
        "Area": 4,
        "Slot": 5,
        "ID": 21,
        "Price": 20000000,
        "Size": 1,
        "FirstSeen": 1739372598,
        "LastSeen": 1739926204,
        "State": 0,
        "Participate": 0,
        "Winner": 0,
        "EndTime": 0,
        "UpdateTime": 0,
        "PurchaseType": 2,
        "RegionType": 2
    },
    {
        "Server": 1174,
        "Area": 4,
        "Slot": 11,
        "ID": 2,
        "Price": 19000000,
        "Size": 1,
        "FirstSeen": 1739725273,
        "LastSeen": 1739926204,
        "State": 0,
        "Participate": 0,
        "Winner": 0,
        "EndTime": 0,
        "UpdateTime": 0,
        "PurchaseType": 2,
        "RegionType": 2
    },
    {
        "Server": 1174,
        "Area": 4,
        "Slot": 13,
        "ID": 12,
        "Price": 50000000,
        "Size": 2,
        "FirstSeen": 1739884187,
        "LastSeen": 1739926205,
        "State": 0,
        "Participate": 0,
        "Winner": 0,
        "EndTime": 0,
        "UpdateTime": 0,
        "PurchaseType": 2,
        "RegionType": 2
    },
    {
        "Server": 1174,
        "Area": 4,
        "Slot": 17,
        "ID": 18,
        "Price": 17000000,
        "Size": 1,
        "FirstSeen": 1739077311,
        "LastSeen": 1739926205,
        "State": 0,
        "Participate": 0,
        "Winner": 0,
        "EndTime": 0,
        "UpdateTime": 0,
        "PurchaseType": 2,
        "RegionType": 0
    },
    {
        "Server": 1174,
        "Area": 4,
        "Slot": 19,
        "ID": 26,
        "Price": 19000000,
        "Size": 1,
        "FirstSeen": 1739361734,
        "LastSeen": 1739926206,
        "State": 0,
        "Participate": 0,
        "Winner": 0,
        "EndTime": 0,
        "UpdateTime": 0,
        "PurchaseType": 2,
        "RegionType": 0
    },
    {
        "Server": 1174,
        "Area": 4,
        "Slot": 28,
        "ID": 17,
        "Price": 18000000,
        "Size": 1,
        "FirstSeen": 1739797274,
        "LastSeen": 1739926207,
        "State": 0,
        "Participate": 0,
        "Winner": 0,
        "EndTime": 0,
        "UpdateTime": 0,
        "PurchaseType": 2,
        "RegionType": 0
    }
]