[
    {
        "Server": 1060,
        "Area": 0,
        "Slot": 1,
        "ID": 36,
        "Price": 20000000,
        "Size": 1,
        "FirstSeen": 1745906456,
        "LastSeen": 1746928005,
        "State": 2,
        "Participate": 80,
        "Winner": 54,
        "EndTime": 1747062000,
        "UpdateTime": 1746876315,
        "PurchaseType": 2,
        "RegionType": 2
    },
    {
        "Server": 1060,
        "Area": 0,
        "Slot": 6,
        "ID": 30,
        "Price": 20000000,
        "Size": 1,
        "FirstSeen": 1746532823,
        "LastSeen": 1746928006,
        "State": 0,
        "Participate": 0,
        "Winner": 0,
        "EndTime": 0,
        "UpdateTime": 0,
        "PurchaseType": 2,
        "RegionType": 2
    },
    {
        "Server": 1060,
        "Area": 0,
        "Slot": 21,
        "ID": 31,
        "Price": 19000000,
        "Size": 1,
        "FirstSeen": 1746543691,
        "LastSeen": 1746928008,
        "State": 0,
        "Participate": 0,
        "Winner": 0,
        "EndTime": 0,
        "UpdateTime": 0,
        "PurchaseType": 2,
        "RegionType": 1
    },
    {
        "Server": 1060,
        "Area": 2,
        "Slot": 22,
        "ID": 4,
        "Price": 19000000,
        "Size": 1,
        "FirstSeen": 1746849651,
        "LastSeen": 1746928020,
        "State": 0,
        "Participate": 0,
        "Winner": 0,
        "EndTime": 0,
        "UpdateTime": 0,
        "PurchaseType": 2,
        "RegionType": 1
    },
    {
        "Server": 1060,
        "Area": 3,
        "Slot": 8,
        "ID": 43,
        "Price": 17000000,
        "Size": 1,
        "FirstSeen": 1746775745,
        "LastSeen": 1746928023,
        "State": 0,
        "Participate": 0,
        "Winner": 0,
        "EndTime": 0,
        "UpdateTime": 0,
        "PurchaseType": 2,
        "RegionType": 2
    },
    {
        "Server": 1060,
        "Area": 4,
        "Slot": 10,
        "ID": 37,
        "Price": 19000000,
        "Size": 1,
        "FirstSeen": 1746604905,
        "LastSeen": 1746928027,
        "State": 0,
        "Participate": 0,
        "Winner": 0,
        "EndTime": 0,
        "UpdateTime": 0,
        "PurchaseType": 2,
        "RegionType": 2
    },
    {
        "Server": 1060,
        "Area": 4,
        "Slot": 11,
        "ID": 17,
        "Price": 18000000,
        "Size": 1,
        "FirstSeen": 1746511253,
        "LastSeen": 1746928028,
        "State": 0,
        "Participate": 0,
        "Winner": 0,
        "EndTime": 0,
        "UpdateTime": 0,
        "PurchaseType": 2,
        "RegionType": 2
    },
    {
        "Server": 1060,
        "Area": 4,
        "Slot": 14,
        "ID": 26,
        "Price": 19000000,
        "Size": 1,
        "FirstSeen": 1746882130,
        "LastSeen": 1746928028,
        "State": 0,
        "Participate": 0,
        "Winner": 0,
        "EndTime": 0,
        "UpdateTime": 0,
        "PurchaseType": 2,
        "RegionType": 2
    },
    {
        "Server": 1060,
        "Area": 4,
        "Slot": 21,
        "ID": 48,
        "Price": 17000000,
        "Size": 1,
        "FirstSeen": 1746821236,
        "LastSeen": 1746928029,
        "State": 0,
        "Participate": 0,
        "Winner": 0,
        "EndTime": 0,
        "UpdateTime": 0,
        "PurchaseType": 2,
        "RegionType": 1
    }
]