[
    {
        "Area": 0,
        "ID": 36,
        "Slot": 1,
        "RegionType": 2,
        "Size": 1,
        "Server": 1060,
        "Purchase_endtime": 1746716400
    },
    {
        "Area": 0,
        "ID": 36,
        "Slot": 4,
        "RegionType": 2,
        "Size": 1,
        "Server": 1060,
        "Purchase_endtime": 1746716400
    },
    {
        "Area": 0,
        "ID": 30,
        "Slot": 6,
        "RegionType": 2,
        "Size": 1,
        "Server": 1060,
        "Purchase_endtime": 1747494000
    },
    {
        "Area": 0,
        "ID": 31,
        "Slot": 21,
        "RegionType": 1,
        "Size": 1,
        "Server": 1060,
        "Purchase_endtime": 1747494000
    },
    {
        "Area": 2,
        "ID": 12,
        "Slot": 6,
        "RegionType": 2,
        "Size": 1,
        "Server": 1060,
        "Purchase_endtime": 1746716400
    },
    {
        "Area": 2,
        "ID": 55,
        "Slot": 17,
        "RegionType": 0,
        "Size": 1,
        "Server": 1060,
        "Purchase_endtime": 1746716400
    },
    {
        "Area": 2,
        "ID": 42,
        "Slot": 26,
        "RegionType": 2,
        "Size": 1,
        "Server": 1060,
        "Purchase_endtime": 1746716400
    },
    {
        "Area": 3,
        "ID": 28,
        "Slot": 9,
        "RegionType": 2,
        "Size": 1,
        "Server": 1060,
        "Purchase_endtime": 1746716400
    },
    {
        "Area": 4,
        "ID": 37,
        "Slot": 10,
        "RegionType": 2,
        "Size": 1,
        "Server": 1060,
        "Purchase_endtime": 1747494000
    },
    {
        "Area": 4,
        "ID": 17,
        "Slot": 11,
        "RegionType": 2,
        "Size": 1,
        "Server": 1060,
        "Purchase_endtime": 1747494000
    }
]